setup.cfg
setup.py
django_mako_plus/__init__.py
django_mako_plus/__main__.py
django_mako_plus/apps.py
django_mako_plus/command.py
django_mako_plus/context_processors.py
django_mako_plus/convenience.py
django_mako_plus/decorators.py
django_mako_plus/defaults.py
django_mako_plus/engine.py
django_mako_plus/exceptions.py
django_mako_plus/filters.py
django_mako_plus/http.py
django_mako_plus/middleware.py
django_mako_plus/models.py
django_mako_plus/signals.py
django_mako_plus/tags.py
django_mako_plus/urls.py
django_mako_plus/version.py
django_mako_plus.egg-info/PKG-INFO
django_mako_plus.egg-info/SOURCES.txt
django_mako_plus.egg-info/dependency_links.txt
django_mako_plus.egg-info/entry_points.txt
django_mako_plus.egg-info/requires.txt
django_mako_plus.egg-info/top_level.txt
django_mako_plus/app_template/__init__.py
django_mako_plus/app_template/admin.py
django_mako_plus/app_template/apps.py
django_mako_plus/app_template/models.py
django_mako_plus/app_template/tests.py
django_mako_plus/app_template/media/python.png
django_mako_plus/app_template/migrations/__init__.py
django_mako_plus/app_template/scripts/index.js
django_mako_plus/app_template/styles/base.css
django_mako_plus/app_template/styles/index.css
django_mako_plus/app_template/templates/base.htm
django_mako_plus/app_template/templates/base_ajax.htm
django_mako_plus/app_template/templates/index.html
django_mako_plus/app_template/views/__init__.py
django_mako_plus/app_template/views/index.py
django_mako_plus/converter/__init__.py
django_mako_plus/converter/base.py
django_mako_plus/converter/converters.py
django_mako_plus/converter/decorators.py
django_mako_plus/converter/info.py
django_mako_plus/converter/parameter.py
django_mako_plus/management/__init__.py
django_mako_plus/management/mixins.py
django_mako_plus/management/commands/__init__.py
django_mako_plus/management/commands/dmp.py
django_mako_plus/management/commands/dmp_cleanup.py
django_mako_plus/management/commands/dmp_collectstatic.py
django_mako_plus/management/commands/dmp_makemessages.py
django_mako_plus/management/commands/dmp_startapp.py
django_mako_plus/management/commands/dmp_startproject.py
django_mako_plus/management/commands/dmp_webpack.py
django_mako_plus/project_template/manage.py-tpl
